consortia_commons/__init__.py
consortia_commons/file/__init__.py
consortia_commons/object/__init__.py
consortia_commons/rest/__init__.py
consortia_commons/string/__init__.py
consortia_commons/ubkg/__init__.py
consortia_commons-1.0.7.dist-info/METADATA
consortia_commons-1.0.7.dist-info/WHEEL
consortia_commons-1.0.7.dist-info/top_level.txt
consortia_commons-1.0.7.dist-info/RECORD
