Metadata-Version: 2.1
Name: consortia-commons
Version: 1.0.7
Summary: The common code supporting the web services in the consortia.
Home-page: https://github.com/x-atlas-consortia/commons
Author: Atlas Consortia
Author-email: api-developers@hubmapconsortium.org
Classifier: Programming Language :: Python :: 3
Classifier: Operating System :: OS Independent
Requires-Python: >=3.6
Requires-Dist: Flask (>=2.1.3)
Requires-Dist: jsonref (==0.3.0)
Requires-Dist: jsonschema (>=3.2.0)
Requires-Dist: neo4j (>=4.2.1)
Requires-Dist: pytz (>=2021.1)
Requires-Dist: property (>=2.2)
Requires-Dist: globus-sdk (>=1.9.0)
Requires-Dist: prov (>=1.5.1)
Requires-Dist: requests (>=2.22.0)
Requires-Dist: PyYAML (>=5.3.1)
